taskchampion_py-2.0.2.dist-info/METADATA
taskchampion_py-2.0.2.dist-info/WHEEL
taskchampion_py-2.0.2.dist-info/licenses/LICENSE
taskchampion.libs/libgcc_s-e52197c3.so.1
taskchampion/__init__.py
taskchampion/__init__.pyi
taskchampion/py.typed
taskchampion/taskchampion.pypy39-pp73-aarch64-linux-gnu.so
taskchampion_py-2.0.2.dist-info/RECORD
