Metadata-Version: 2.4
Name: taskchampion-py
Version: 2.0.2
Classifier: Programming Language :: Rust
Classifier: Programming Language :: Python :: Implementation :: CPython
Classifier: Programming Language :: Python :: Implementation :: PyPy
License-File: LICENSE
Author-email: Illya Laifu <illyalaifu@gmail.com>, "Dustin J. Mitchell" <dustin@v.igoro.us>
Requires-Python: >=3.9
Project-URL: homepage, https://gothenburgbitfactory.org/taskchampion
Project-URL: repository, https://github.com/GothenburgBitFactory/taskchampion-py
Project-URL: changelog, https://github.com/GothenburgBitFactory/taskchampion-py/releases
